pubproxpy/__init__.py
pubproxpy/_constants.py
pubproxpy/_singleton.py
pubproxpy/errors.py
pubproxpy/fetcher.py
pubproxpy/types.py
pubproxpy-2.0.2.dist-info/LICENSE
pubproxpy-2.0.2.dist-info/WHEEL
pubproxpy-2.0.2.dist-info/METADATA
pubproxpy-2.0.2.dist-info/RECORD
