Metadata-Version: 2.1
Name: pubproxpy
Version: 2.0.2
Summary: An easy to use Python wrapper for pubproxy.com
Home-page: https://github.com/LovecraftianHorror/pubproxpy
License: GPL-3.0
Keywords: proxy api,pubproxy,public proxy,pubproxy api,scraping
Author: LovecraftianHorror
Author-email: LovecraftianHorror@pm.me
Requires-Python: >=3.7,<4.0
Classifier: License :: OSI Approved :: GNU General Public License v3 (GPLv3)
Classifier: Programming Language :: Python :: 3
Classifier: Programming Language :: Python :: 3.7
Classifier: Programming Language :: Python :: 3.8
Classifier: Programming Language :: Python :: 3.9
Requires-Dist: requests (>=2.22,<3.0)
Project-URL: Repository, https://github.com/LovecraftianHorror/pubproxpy
